<?xml version="1.0" encoding="utf-8" ?>
<dwsync>
<file name="factura.php" local="129866689178097236" remote="129866689170000000" testing="129866689170000000" />
<file name="detfact.php" local="130294433199600160" remote="130294433190000000" testing="130294433190000000" />
<file name="verfact.php" local="130220304760949431" remote="130220304760000000" testing="130220304760000000" />
<file name="actufact.php" local="130227192558321760" remote="130227192550000000" testing="130227192550000000" />
<file name="listfact.php" local="129820890313991216" remote="129820890310000000" testing="129820890310000000" />
<file name="edit.php" local="129811578432093424" remote="129811578430000000" testing="0" />
<file name="actudatos.php" local="130326313353805676" remote="130326313350000000" testing="130326313350000000" />
<file name="facturacion.php" local="130205393539726474" remote="130205393530000000" testing="130205393530000000" />
<file name="factmes.php" local="130250631763165687" remote="130250631760000000" testing="130250631760000000" />
<file name="factorden.php" local="130259851604971050" remote="130259851600000000" testing="130259851600000000" />
<file name="conordfact.php" local="129943743392137473" remote="129943743390000000" testing="129943743390000000" />
<file name="facmesestado.php" local="130141438122650204" remote="130141438120000000" testing="130141438120000000" />
<file name="factcliente.php" local="130113759770058407" remote="130113759770000000" testing="130113759770000000" />
<file name="inventario.php" local="130329155350928093" remote="130329155350000000" testing="130329155350000000" />
<file name="factclientes.php" local="130184718861545007" remote="130184718860000000" testing="130184718860000000" />
<file name="boleta.php" local="130215146112284464" remote="130215146110000000" testing="130215146110000000" />
<file name="detbole.php" local="130215771388243879" remote="130215771380000000" testing="130215771380000000" />
<file name="verbole.php" local="130235630043685282" remote="130235630040000000" testing="130235630040000000" />
<file name="factvarios.php" local="130221139261434594" remote="130221139260000000" testing="130221139260000000" />
<file name="index.html" local="130284352640082848" remote="130284352640000000" testing="130284352640000000" />
<file name="mi_php.php" local="130286583475820236" remote="130286583470000000" testing="130286583470000000" />
<file name="factclienorden.php" local="130295467174074880" remote="130295467170000000" testing="130295467170000000" />
</dwsync>